{
  "timestamp": "2026-07-05T11:02:56.725815",
  "total_jobs": 50,
  "filter": "IT/Tech/Software Development Jobs Only",
  "sources": [
    "LinkedIn",
    "Twitter/X",
    "Reddit",
    "GitHub Jobs",
    "RemoteOK",
    "Dev.to",
    "We Work Remotely",
    "ArbeitNow",
    "Stack Overflow",
    "Indeed"
  ],
  "jobs": [
    {
      "title": "Not specified",
      "company": "Konkan Development Society",
      "location": "Remote",
      "salary": "Not specified",
      "description": "<p><strong>Company Description</strong> Konkan Development Society is an organization based along Raj Bhavan University Road in Taleigao, Goa, India, serving the broader Konkan region. The Society is ",
      "source": "RemoteOK",
      "url": "https://remoteOK.com/remote-jobs/remote-jobs-konkan-development-society-1134490",
      "posted_at": "2026-07-04T07:58:52+00:00"
    },
    {
      "title": "Not specified",
      "company": "City of Campbell River",
      "location": "Remote",
      "salary": "Not specified",
      "description": "<strong>Organization<br><br></strong>City of Campbell River<br><br><strong>Region<br><br></strong>British Columbia<br><br><strong>Application Deadline<br><br></strong>July 26, 2026<br><br><strong>Type",
      "source": "RemoteOK",
      "url": "https://remoteOK.com/remote-jobs/remote-watch-clerk-city-of-campbell-river-1134493",
      "posted_at": "2026-07-03T12:48:22+00:00"
    },
    {
      "title": "Not specified",
      "company": "Unigo",
      "location": "Remote",
      "salary": "Not specified",
      "description": "Top Careers That Are Safe From AI<br><br>With the rise of Artificial Intelligence and its expanding capacities, workers everywhere are asking themselves the same question:...<br/><br/>Please mention t",
      "source": "RemoteOK",
      "url": "https://remoteOK.com/remote-jobs/remote-5-ways-be-a-better-listener-unigo-1134411",
      "posted_at": "2026-07-02T22:18:42+00:00"
    },
    {
      "title": "Not specified",
      "company": "HomeExchange",
      "location": "Remote",
      "salary": "Not specified",
      "description": "<strong><strong>HomeExchange is always looking for talented people, donât hesitate to apply!</strong></strong><br/><br/>Please mention the word **FANTASTICALLY** and tag RMjAuMTI3LjIzOC44Mg== when a",
      "source": "RemoteOK",
      "url": "https://remoteOK.com/remote-jobs/remote-spontaneous-application-homeexchange-1134434",
      "posted_at": "2026-07-02T09:52:28+00:00"
    },
    {
      "title": "Not specified",
      "company": "Bluefield Daily Telegraph",
      "location": "Remote",
      "salary": "Not specified",
      "description": "Want a high-paying job but donât have time to complete a four-year degree? If you choose the right...<br><br>Read more<br><br>5 Ways to Be a Better Listener (And Improve Your Job Search)<br><br>Shut",
      "source": "RemoteOK",
      "url": "https://remoteOK.com/remote-jobs/remote-12-jobs-that-pay-well-without-a-degree-bluefield-daily-telegraph-1134387",
      "posted_at": "2026-07-01T23:06:25+00:00"
    },
    {
      "title": "Not specified",
      "company": "Department of Justice QLD",
      "location": "Remote",
      "salary": "Not specified",
      "description": "The Registrar role presents an exciting opportunity to actively contribute to the modernisation and improvement of the court system, emphasising safety, innovation, efficiency, and enhanced access to ",
      "source": "RemoteOK",
      "url": "https://remoteOK.com/remote-jobs/remote-registrar-department-of-justice-qld-1134376",
      "posted_at": "2026-07-01T14:25:47+00:00"
    },
    {
      "title": "Not specified",
      "company": "Atlantic Oceanic LLC",
      "location": "Remote",
      "salary": "Not specified",
      "description": "<br><br><p>We are looking crew for AHTS. 14000 HP </p><p><br></p><p>Please send CV to power@atlanticoceanic.com &amp; deansmith@atlanticoceanic.com</p><p><br></p><p>AHTS located in Bahamas</p><p><br><",
      "source": "RemoteOK",
      "url": "https://remoteOK.com/remote-jobs/remote-full-crew-atlantic-oceanic-llc-1134321",
      "posted_at": "2026-06-30T17:41:38+00:00"
    },
    {
      "title": "Software Engineer (All Levels)",
      "company": "Blossom",
      "location": "New York, NY",
      "salary": "Not specified",
      "description": "LinkedIn Job - Software Engineer (All Levels)",
      "source": "LinkedIn",
      "url": "https://www.linkedin.com/jobs/view/software-engineer-all-levels-at-blossom-4432033379?position=1&pageNum=0&refId=2nRbZYTxMxLsycBjri4naA%3D%3D&trackingId=hJ40iz2MuseWmTJHiXEYfA%3D%3D",
      "posted_at": "2026-07-05T11:02:23.442467"
    },
    {
      "title": "Software Engineer",
      "company": "QinetiQ",
      "location": "Manchester, England, United Kingdom",
      "salary": "Not specified",
      "description": "LinkedIn Job - Software Engineer",
      "source": "LinkedIn",
      "url": "https://uk.linkedin.com/jobs/view/software-engineer-at-qinetiq-4344103547?position=2&pageNum=0&refId=2nRbZYTxMxLsycBjri4naA%3D%3D&trackingId=GV%2Fn7R4JEsPKtgPYzKFlKQ%3D%3D",
      "posted_at": "2026-07-05T11:02:23.442725"
    },
    {
      "title": "Software Engineer",
      "company": "Nuvo",
      "location": "New York, NY",
      "salary": "Not specified",
      "description": "LinkedIn Job - Software Engineer",
      "source": "LinkedIn",
      "url": "https://www.linkedin.com/jobs/view/software-engineer-at-nuvo-4378357766?position=3&pageNum=0&refId=2nRbZYTxMxLsycBjri4naA%3D%3D&trackingId=%2B8uNhf%2FuPAEoZ1CVJKh4Uw%3D%3D",
      "posted_at": "2026-07-05T11:02:23.442925"
    },
    {
      "title": "Software Engineer",
      "company": "Oso",
      "location": "New York, NY",
      "salary": "Not specified",
      "description": "LinkedIn Job - Software Engineer",
      "source": "LinkedIn",
      "url": "https://www.linkedin.com/jobs/view/software-engineer-at-oso-4363726700?position=4&pageNum=0&refId=2nRbZYTxMxLsycBjri4naA%3D%3D&trackingId=SVE85PsMZ57M28FFtyLtOg%3D%3D",
      "posted_at": "2026-07-05T11:02:23.443120"
    },
    {
      "title": "Software Engineer",
      "company": "Moab",
      "location": "New York, NY",
      "salary": "Not specified",
      "description": "LinkedIn Job - Software Engineer",
      "source": "LinkedIn",
      "url": "https://www.linkedin.com/jobs/view/software-engineer-at-moab-4318517031?position=5&pageNum=0&refId=2nRbZYTxMxLsycBjri4naA%3D%3D&trackingId=arl6fXaMpIUyx%2B7lU2%2F7Dw%3D%3D",
      "posted_at": "2026-07-05T11:02:23.443296"
    },
    {
      "title": "Software Developer",
      "company": "Weekday (YC W21)",
      "location": "New York, NY",
      "salary": "Not specified",
      "description": "LinkedIn Job - Software Developer",
      "source": "LinkedIn",
      "url": "https://www.linkedin.com/jobs/view/software-developer-at-weekday-yc-w21-4432097763?position=6&pageNum=0&refId=2nRbZYTxMxLsycBjri4naA%3D%3D&trackingId=3RLTBcBsDHYoxpX7ZVua6g%3D%3D",
      "posted_at": "2026-07-05T11:02:23.443486"
    },
    {
      "title": "Custom Software Engineer",
      "company": "Accenture in India",
      "location": "Hyderabad, Telangana, India",
      "salary": "Not specified",
      "description": "LinkedIn Job - Custom Software Engineer",
      "source": "LinkedIn",
      "url": "https://in.linkedin.com/jobs/view/custom-software-engineer-at-accenture-in-india-4435834842?position=7&pageNum=0&refId=2nRbZYTxMxLsycBjri4naA%3D%3D&trackingId=M%2BUvuxabpGmPXuhqrYvg9w%3D%3D",
      "posted_at": "2026-07-05T11:02:23.443643"
    },
    {
      "title": "Software Engineer",
      "company": "Chalk",
      "location": "New York, NY",
      "salary": "Not specified",
      "description": "LinkedIn Job - Software Engineer",
      "source": "LinkedIn",
      "url": "https://www.linkedin.com/jobs/view/software-engineer-at-chalk-4406548495?position=9&pageNum=0&refId=2nRbZYTxMxLsycBjri4naA%3D%3D&trackingId=maJ%2FTDSxIuzczoySUc%2BrNg%3D%3D",
      "posted_at": "2026-07-05T11:02:23.443959"
    },
    {
      "title": "Software Engineer",
      "company": "Voltai",
      "location": "Palo Alto, CA",
      "salary": "Not specified",
      "description": "LinkedIn Job - Software Engineer",
      "source": "LinkedIn",
      "url": "https://www.linkedin.com/jobs/view/software-engineer-at-voltai-4318514364?position=10&pageNum=0&refId=2nRbZYTxMxLsycBjri4naA%3D%3D&trackingId=40rOWdRwxzZeBMsJSWFVqg%3D%3D",
      "posted_at": "2026-07-05T11:02:23.444115"
    },
    {
      "title": "Python Developer",
      "company": "Infosys",
      "location": "Bengaluru, Karnataka, India",
      "salary": "Not specified",
      "description": "LinkedIn Job - Python Developer",
      "source": "LinkedIn",
      "url": "https://in.linkedin.com/jobs/view/python-developer-at-infosys-4323369504?position=1&pageNum=0&refId=4%2FqCdIbBuuBsVJhKiZY8AA%3D%3D&trackingId=FON3D63MNztyL4wfJ4BEbg%3D%3D",
      "posted_at": "2026-07-05T11:02:26.542330"
    },
    {
      "title": "Associate - Python Data Engineer - GDC",
      "company": "PwC India",
      "location": "Kolkata, West Bengal, India",
      "salary": "Not specified",
      "description": "LinkedIn Job - Associate - Python Data Engineer - GDC",
      "source": "LinkedIn",
      "url": "https://in.linkedin.com/jobs/view/associate-python-data-engineer-gdc-at-pwc-india-4291069034?position=2&pageNum=0&refId=4%2FqCdIbBuuBsVJhKiZY8AA%3D%3D&trackingId=%2FQpTh2KZ558s9lOW697JOA%3D%3D",
      "posted_at": "2026-07-05T11:02:26.542582"
    },
    {
      "title": "Junior Python Developer",
      "company": "IBM",
      "location": "Kochi, Kerala, India",
      "salary": "Not specified",
      "description": "LinkedIn Job - Junior Python Developer",
      "source": "LinkedIn",
      "url": "https://in.linkedin.com/jobs/view/junior-python-developer-at-ibm-4417202156?position=3&pageNum=0&refId=4%2FqCdIbBuuBsVJhKiZY8AA%3D%3D&trackingId=mk76A4C7MuWqfBknqHccBQ%3D%3D",
      "posted_at": "2026-07-05T11:02:26.542788"
    },
    {
      "title": "Python Developer",
      "company": "Deloitte",
      "location": "Bengaluru, Karnataka, India",
      "salary": "Not specified",
      "description": "LinkedIn Job - Python Developer",
      "source": "LinkedIn",
      "url": "https://in.linkedin.com/jobs/view/python-developer-at-deloitte-4427346679?position=4&pageNum=0&refId=4%2FqCdIbBuuBsVJhKiZY8AA%3D%3D&trackingId=g9aqjo%2BgpOnBx8nu%2FQiVZg%3D%3D",
      "posted_at": "2026-07-05T11:02:26.543005"
    },
    {
      "title": "Python Developer",
      "company": "hackajob",
      "location": "London, England, United Kingdom",
      "salary": "Not specified",
      "description": "LinkedIn Job - Python Developer",
      "source": "LinkedIn",
      "url": "https://uk.linkedin.com/jobs/view/python-developer-at-hackajob-4425526234?position=7&pageNum=0&refId=4%2FqCdIbBuuBsVJhKiZY8AA%3D%3D&trackingId=f8v%2FttrgS9DXdOa5nA8vxw%3D%3D",
      "posted_at": "2026-07-05T11:02:26.543568"
    },
    {
      "title": "Python Django Developer",
      "company": "Infosys",
      "location": "Bengaluru East, Karnataka, India",
      "salary": "Not specified",
      "description": "LinkedIn Job - Python Django Developer",
      "source": "LinkedIn",
      "url": "https://in.linkedin.com/jobs/view/python-django-developer-at-infosys-4435532023?position=8&pageNum=0&refId=4%2FqCdIbBuuBsVJhKiZY8AA%3D%3D&trackingId=dbH%2BMA3aPDLrsgOq2KaaXw%3D%3D",
      "posted_at": "2026-07-05T11:02:26.543724"
    },
    {
      "title": "Python Developer",
      "company": "PwC",
      "location": "Bengaluru, Karnataka, India",
      "salary": "Not specified",
      "description": "LinkedIn Job - Python Developer",
      "source": "LinkedIn",
      "url": "https://in.linkedin.com/jobs/view/python-developer-at-pwc-4426098192?position=10&pageNum=0&refId=4%2FqCdIbBuuBsVJhKiZY8AA%3D%3D&trackingId=ob%2BgPzqlnE7W7v84xymc9A%3D%3D",
      "posted_at": "2026-07-05T11:02:26.544037"
    },
    {
      "title": "Javascript Developer",
      "company": "SpiceGems",
      "location": "Kota, Rajasthan, India",
      "salary": "Not specified",
      "description": "LinkedIn Job - Javascript Developer",
      "source": "LinkedIn",
      "url": "https://in.linkedin.com/jobs/view/javascript-developer-at-spicegems-4407905726?position=1&pageNum=0&refId=Yyy6EiOI9K%2F5F6v%2FiTM%2F4Q%3D%3D&trackingId=PiAhCPj8Ewz1uV6om3Cwiw%3D%3D",
      "posted_at": "2026-07-05T11:02:29.342152"
    },
    {
      "title": "Web Developer",
      "company": "Accenture in India",
      "location": "Pune Division, Maharashtra, India",
      "salary": "Not specified",
      "description": "LinkedIn Job - Web Developer",
      "source": "LinkedIn",
      "url": "https://in.linkedin.com/jobs/view/web-developer-at-accenture-in-india-4380772844?position=2&pageNum=0&refId=Yyy6EiOI9K%2F5F6v%2FiTM%2F4Q%3D%3D&trackingId=XTO71d%2FTHyGQpYH67Vn0CQ%3D%3D",
      "posted_at": "2026-07-05T11:02:29.342405"
    },
    {
      "title": "Web Developer",
      "company": "Dikonia",
      "location": "Sahibzada Ajit Singh Nagar, Punjab, India",
      "salary": "Not specified",
      "description": "LinkedIn Job - Web Developer",
      "source": "LinkedIn",
      "url": "https://in.linkedin.com/jobs/view/web-developer-at-dikonia-4306113558?position=4&pageNum=0&refId=Yyy6EiOI9K%2F5F6v%2FiTM%2F4Q%3D%3D&trackingId=O21bfzSK6Oupf72963TzFQ%3D%3D",
      "posted_at": "2026-07-05T11:02:29.342825"
    },
    {
      "title": "Software Developer",
      "company": "PureSpectrum",
      "location": "Jaipur, Rajasthan, India",
      "salary": "Not specified",
      "description": "LinkedIn Job - Software Developer",
      "source": "LinkedIn",
      "url": "https://in.linkedin.com/jobs/view/software-developer-at-purespectrum-4407126467?position=5&pageNum=0&refId=Yyy6EiOI9K%2F5F6v%2FiTM%2F4Q%3D%3D&trackingId=qigk28CeoYhzNwQzEoc0Rw%3D%3D",
      "posted_at": "2026-07-05T11:02:29.342985"
    },
    {
      "title": "Java Script Programmer",
      "company": "Amla Commerce (Creator of Artifi and Znode)",
      "location": "Nagpur, Maharashtra, India",
      "salary": "Not specified",
      "description": "LinkedIn Job - Java Script Programmer",
      "source": "LinkedIn",
      "url": "https://in.linkedin.com/jobs/view/java-script-programmer-at-amla-commerce-creator-of-artifi-and-znode-4332099617?position=6&pageNum=0&refId=Yyy6EiOI9K%2F5F6v%2FiTM%2F4Q%3D%3D&trackingId=D4G%2FvmrmIKZEh4hiRnUQQw%3D%3D",
      "posted_at": "2026-07-05T11:02:29.343136"
    },
    {
      "title": "Front-End Developer",
      "company": "Websultanate Software Technologies Pvt Ltd",
      "location": "Lucknow, Uttar Pradesh, India",
      "salary": "Not specified",
      "description": "LinkedIn Job - Front-End Developer",
      "source": "LinkedIn",
      "url": "https://in.linkedin.com/jobs/view/front-end-developer-at-websultanate-software-technologies-pvt-ltd-4342067213?position=7&pageNum=0&refId=Yyy6EiOI9K%2F5F6v%2FiTM%2F4Q%3D%3D&trackingId=Ebq2QsQX%2BtH%2BnZKiWfm2ZA%3D%3D",
      "posted_at": "2026-07-05T11:02:29.343287"
    },
    {
      "title": "Web Developer",
      "company": "Uniglobe Maya Travels Pvt Ltd",
      "location": "Ladwa, Haryana, India",
      "salary": "Not specified",
      "description": "LinkedIn Job - Web Developer",
      "source": "LinkedIn",
      "url": "https://in.linkedin.com/jobs/view/web-developer-at-uniglobe-maya-travels-pvt-ltd-4428468317?position=8&pageNum=0&refId=Yyy6EiOI9K%2F5F6v%2FiTM%2F4Q%3D%3D&trackingId=H8FO9SUof9ma5Db828Gkpg%3D%3D",
      "posted_at": "2026-07-05T11:02:29.343497"
    },
    {
      "title": "Frontend Developers",
      "company": "AI CERTs® - India",
      "location": "Gandhinagar, Gujarat, India",
      "salary": "Not specified",
      "description": "LinkedIn Job - Frontend Developers",
      "source": "LinkedIn",
      "url": "https://in.linkedin.com/jobs/view/frontend-developers-at-ai-certs%C2%AE-india-4412283340?position=9&pageNum=0&refId=Yyy6EiOI9K%2F5F6v%2FiTM%2F4Q%3D%3D&trackingId=cgso2qMtx%2B2mDqooMYJ7NQ%3D%3D",
      "posted_at": "2026-07-05T11:02:29.343707"
    },
    {
      "title": "Software Engineer - Front End",
      "company": "SmartBear",
      "location": "Ahmedabad, Gujarat, India",
      "salary": "Not specified",
      "description": "LinkedIn Job - Software Engineer - Front End",
      "source": "LinkedIn",
      "url": "https://in.linkedin.com/jobs/view/software-engineer-front-end-at-smartbear-4425848073?position=10&pageNum=0&refId=Yyy6EiOI9K%2F5F6v%2FiTM%2F4Q%3D%3D&trackingId=5WE%2FZ8%2Fxl6zybCu4nOUDdg%3D%3D",
      "posted_at": "2026-07-05T11:02:29.343862"
    },
    {
      "title": "Data Scientist",
      "company": "malomatia",
      "location": "Doha, Qatar",
      "salary": "Not specified",
      "description": "LinkedIn Job - Data Scientist",
      "source": "LinkedIn",
      "url": "https://qa.linkedin.com/jobs/view/data-scientist-at-malomatia-4431381395?position=1&pageNum=0&refId=pLyN%2BJmAJR838NQN%2B7MQoQ%3D%3D&trackingId=pyu5lXGPjHoVlVrwuv3nJw%3D%3D",
      "posted_at": "2026-07-05T11:02:32.119697"
    },
    {
      "title": "Data Scientist",
      "company": "Qatar Insurance Group",
      "location": "Doha, Qatar",
      "salary": "Not specified",
      "description": "LinkedIn Job - Data Scientist",
      "source": "LinkedIn",
      "url": "https://qa.linkedin.com/jobs/view/data-scientist-at-qatar-insurance-group-4427362257?position=2&pageNum=0&refId=pLyN%2BJmAJR838NQN%2B7MQoQ%3D%3D&trackingId=EwmFV3Z69Zp60tSITS5u7w%3D%3D",
      "posted_at": "2026-07-05T11:02:32.119958"
    },
    {
      "title": "Data Scientist",
      "company": "Avrioc Technologies",
      "location": "Abu Dhabi Emirate, United Arab Emirates",
      "salary": "Not specified",
      "description": "LinkedIn Job - Data Scientist",
      "source": "LinkedIn",
      "url": "https://ae.linkedin.com/jobs/view/data-scientist-at-avrioc-technologies-4432536431?position=3&pageNum=0&refId=pLyN%2BJmAJR838NQN%2B7MQoQ%3D%3D&trackingId=s77GZmddgqp8k37hQUqRIw%3D%3D",
      "posted_at": "2026-07-05T11:02:32.120174"
    },
    {
      "title": "Data Scientist",
      "company": "Huspy",
      "location": "Abu Dhabi, Abu Dhabi Emirate, United Arab Emirates",
      "salary": "Not specified",
      "description": "LinkedIn Job - Data Scientist",
      "source": "LinkedIn",
      "url": "https://ae.linkedin.com/jobs/view/data-scientist-at-huspy-4407904822?position=4&pageNum=0&refId=pLyN%2BJmAJR838NQN%2B7MQoQ%3D%3D&trackingId=zh2NZJeicK1zsd9mC528tg%3D%3D",
      "posted_at": "2026-07-05T11:02:32.120403"
    },
    {
      "title": "Data Scientist",
      "company": "Proton DataLabs",
      "location": "Time, Rogaland, Norway",
      "salary": "Not specified",
      "description": "LinkedIn Job - Data Scientist",
      "source": "LinkedIn",
      "url": "https://no.linkedin.com/jobs/view/data-scientist-at-proton-datalabs-4431637347?position=5&pageNum=0&refId=pLyN%2BJmAJR838NQN%2B7MQoQ%3D%3D&trackingId=vVfnPeNkvFrLlweNgDq1jQ%3D%3D",
      "posted_at": "2026-07-05T11:02:32.120588"
    },
    {
      "title": "Data Scientist",
      "company": "Clio",
      "location": "Calgary, Alberta, Canada",
      "salary": "Not specified",
      "description": "LinkedIn Job - Data Scientist",
      "source": "LinkedIn",
      "url": "https://ca.linkedin.com/jobs/view/data-scientist-at-clio-4426995812?position=7&pageNum=0&refId=pLyN%2BJmAJR838NQN%2B7MQoQ%3D%3D&trackingId=iawkkP3xs4Ohx0aJuTjRhA%3D%3D",
      "posted_at": "2026-07-05T11:02:32.120970"
    },
    {
      "title": "Data Scientist",
      "company": "Saal.ai",
      "location": "Abu Dhabi, Abu Dhabi Emirate, United Arab Emirates",
      "salary": "Not specified",
      "description": "LinkedIn Job - Data Scientist",
      "source": "LinkedIn",
      "url": "https://ae.linkedin.com/jobs/view/data-scientist-at-saal-ai-4422255480?position=8&pageNum=0&refId=pLyN%2BJmAJR838NQN%2B7MQoQ%3D%3D&trackingId=iJyZm%2FM%2FREPoVUtA66KKAA%3D%3D",
      "posted_at": "2026-07-05T11:02:32.121149"
    },
    {
      "title": "Data Scientist",
      "company": "Tracksuit",
      "location": "Auckland, Auckland, New Zealand",
      "salary": "Not specified",
      "description": "LinkedIn Job - Data Scientist",
      "source": "LinkedIn",
      "url": "https://nz.linkedin.com/jobs/view/data-scientist-at-tracksuit-4356213349?position=9&pageNum=0&refId=pLyN%2BJmAJR838NQN%2B7MQoQ%3D%3D&trackingId=WuMDNd4FdZ66VHCkdVJQ%2BQ%3D%3D",
      "posted_at": "2026-07-05T11:02:32.121356"
    },
    {
      "title": "Data Scientist",
      "company": "Viva Tech Solutions",
      "location": "Canada",
      "salary": "Not specified",
      "description": "LinkedIn Job - Data Scientist",
      "source": "LinkedIn",
      "url": "https://ca.linkedin.com/jobs/view/data-scientist-at-viva-tech-solutions-4436334981?position=10&pageNum=0&refId=pLyN%2BJmAJR838NQN%2B7MQoQ%3D%3D&trackingId=nc7H3sUgtEp86BAIgXUOEA%3D%3D",
      "posted_at": "2026-07-05T11:02:32.121538"
    },
    {
      "title": "DevOps Engineer Needed at Kuda Bank",
      "company": "Bankable Wisdom",
      "location": "Nigeria",
      "salary": "Not specified",
      "description": "LinkedIn Job - DevOps Engineer Needed at Kuda Bank",
      "source": "LinkedIn",
      "url": "https://ng.linkedin.com/jobs/view/devops-engineer-needed-at-kuda-bank-at-bankable-wisdom-4431383163?position=1&pageNum=0&refId=GC4wXXVfDshEEg%2FebP5fdg%3D%3D&trackingId=RWGIFVifceXmLYr1kf5p1g%3D%3D",
      "posted_at": "2026-07-05T11:02:35.107220"
    },
    {
      "title": "Devops Engineer",
      "company": "MedReview Inc.",
      "location": "Newport Beach, CA",
      "salary": "Not specified",
      "description": "LinkedIn Job - Devops Engineer",
      "source": "LinkedIn",
      "url": "https://www.linkedin.com/jobs/view/devops-engineer-at-medreview-inc-4399902206?position=2&pageNum=0&refId=GC4wXXVfDshEEg%2FebP5fdg%3D%3D&trackingId=IBbG6DIa0zur60WDVAr9ZQ%3D%3D",
      "posted_at": "2026-07-05T11:02:35.107497"
    },
    {
      "title": "DevOps Engineer",
      "company": "Easebuzz",
      "location": "Pune Division, Maharashtra, India",
      "salary": "Not specified",
      "description": "LinkedIn Job - DevOps Engineer",
      "source": "LinkedIn",
      "url": "https://in.linkedin.com/jobs/view/devops-engineer-at-easebuzz-4218857089?position=3&pageNum=0&refId=GC4wXXVfDshEEg%2FebP5fdg%3D%3D&trackingId=8AUsHyn6Dzb5PAr4HY%2FWjQ%3D%3D",
      "posted_at": "2026-07-05T11:02:35.107710"
    },
    {
      "title": "Junior DevOps Engineer",
      "company": "Work Force Nexus",
      "location": "United Kingdom",
      "salary": "Not specified",
      "description": "LinkedIn Job - Junior DevOps Engineer",
      "source": "LinkedIn",
      "url": "https://uk.linkedin.com/jobs/view/junior-devops-engineer-at-work-force-nexus-4434608736?position=4&pageNum=0&refId=GC4wXXVfDshEEg%2FebP5fdg%3D%3D&trackingId=h5220rfp2wrNKKFd%2Fr%2FZtw%3D%3D",
      "posted_at": "2026-07-05T11:02:35.107908"
    },
    {
      "title": "DevOps Junior Engineer",
      "company": "The Clearing House",
      "location": "Liberty, NY",
      "salary": "Not specified",
      "description": "LinkedIn Job - DevOps Junior Engineer",
      "source": "LinkedIn",
      "url": "https://www.linkedin.com/jobs/view/devops-junior-engineer-at-the-clearing-house-4423565050?position=5&pageNum=0&refId=GC4wXXVfDshEEg%2FebP5fdg%3D%3D&trackingId=tKQEpPQtnrj%2FEy%2FLk7QPbA%3D%3D",
      "posted_at": "2026-07-05T11:02:35.108107"
    },
    {
      "title": "Junior DevOps Engineer",
      "company": "StickEarn",
      "location": "Gambir, Jakarta, Indonesia",
      "salary": "Not specified",
      "description": "LinkedIn Job - Junior DevOps Engineer",
      "source": "LinkedIn",
      "url": "https://id.linkedin.com/jobs/view/junior-devops-engineer-at-stickearn-4435019089?position=6&pageNum=0&refId=GC4wXXVfDshEEg%2FebP5fdg%3D%3D&trackingId=OsGX3Oi36eByWNylwGYJDA%3D%3D",
      "posted_at": "2026-07-05T11:02:35.108328"
    },
    {
      "title": "DevOps Engineer",
      "company": "ClassWallet",
      "location": "United States",
      "salary": "Not specified",
      "description": "LinkedIn Job - DevOps Engineer",
      "source": "LinkedIn",
      "url": "https://www.linkedin.com/jobs/view/devops-engineer-at-classwallet-4429593309?position=7&pageNum=0&refId=GC4wXXVfDshEEg%2FebP5fdg%3D%3D&trackingId=JXZukQb4GOr8sw3N5gfNnw%3D%3D",
      "posted_at": "2026-07-05T11:02:35.108531"
    },
    {
      "title": "Junior DevOps Engineer",
      "company": "Roketin - PT Roketin Kreatif Teknologi",
      "location": "Bandung, West Java, Indonesia",
      "salary": "Not specified",
      "description": "LinkedIn Job - Junior DevOps Engineer",
      "source": "LinkedIn",
      "url": "https://id.linkedin.com/jobs/view/junior-devops-engineer-at-roketin-pt-roketin-kreatif-teknologi-4259853588?position=9&pageNum=0&refId=GC4wXXVfDshEEg%2FebP5fdg%3D%3D&trackingId=g3V%2FS%2BUUa%2BPyFYrw21rUlw%3D%3D",
      "posted_at": "2026-07-05T11:02:35.108941"
    },
    {
      "title": "DevOps Engineer",
      "company": "Pangaea Data",
      "location": "South San Francisco, CA",
      "salary": "Not specified",
      "description": "LinkedIn Job - DevOps Engineer",
      "source": "LinkedIn",
      "url": "https://www.linkedin.com/jobs/view/devops-engineer-at-pangaea-data-4365603600?position=10&pageNum=0&refId=GC4wXXVfDshEEg%2FebP5fdg%3D%3D&trackingId=BMOheLn2lJvgP%2BUYOJ5X3Q%3D%3D",
      "posted_at": "2026-07-05T11:02:35.109139"
    }
  ]
}