{
  "timestamp": "2026-05-02T09:57:34.298784",
  "total_jobs": 40,
  "filter": "IT/Tech/Software Development Jobs Only",
  "sources": [
    "LinkedIn",
    "Twitter/X",
    "Reddit",
    "GitHub Jobs",
    "RemoteOK",
    "Dev.to",
    "We Work Remotely",
    "ArbeitNow",
    "Stack Overflow",
    "Indeed"
  ],
  "jobs": [
    {
      "title": "Not specified",
      "company": "ShipBob, Inc.",
      "location": "Remote",
      "salary": "Not specified",
      "description": "<p><span style=\"font-family: arial, helvetica, sans-serif; font-size: 10pt;\"><span data-contrast=\"none\">As a member of the&nbsp;ShipBob&nbsp;Team, you will...</span><span data-ccp-props=\"{\\\"134233117\\",
      "source": "RemoteOK",
      "url": "https://remoteOK.com/remote-jobs/remote-senior-transportation-specialist-shipbob-inc-1131354",
      "posted_at": "2026-04-28T00:01:08+00:00"
    },
    {
      "title": "Not specified",
      "company": "Fleetio",
      "location": "Remote",
      "salary": "Not specified",
      "description": "A little about usâ¦Fleetio is a modern software platform that helps thousands of organizations worldwide manage their fleet operations. Transportation technology is a hot market, and we're leading th",
      "source": "RemoteOK",
      "url": "https://remoteOK.com/remote-jobs/remote-test-job-fleetio-1131302",
      "posted_at": "2026-04-24T00:00:52+00:00"
    },
    {
      "title": "Software Engineer, New Grad (AI)",
      "company": "Notion",
      "location": "San Francisco, CA",
      "salary": "Not specified",
      "description": "LinkedIn Job - Software Engineer, New Grad (AI)",
      "source": "LinkedIn",
      "url": "https://www.linkedin.com/jobs/view/software-engineer-new-grad-ai-at-notion-4407498584?position=1&pageNum=0&refId=l715izhDauHZ2kxgtRyZ8A%3D%3D&trackingId=n71je1nvTC9v8dLdgse0NQ%3D%3D",
      "posted_at": "2026-05-02T09:57:07.006340"
    },
    {
      "title": "Software Engineer, Airbnb - New Grad",
      "company": "Airbnb",
      "location": "San Francisco, CA",
      "salary": "Not specified",
      "description": "LinkedIn Job - Software Engineer, Airbnb - New Grad",
      "source": "LinkedIn",
      "url": "https://www.linkedin.com/jobs/view/software-engineer-airbnb-new-grad-at-airbnb-4409135057?position=2&pageNum=0&refId=l715izhDauHZ2kxgtRyZ8A%3D%3D&trackingId=jNOHrFnEc%2BgnnaSQ%2BCdHvw%3D%3D",
      "posted_at": "2026-05-02T09:57:07.006648"
    },
    {
      "title": "Software Engineer I",
      "company": "Duolingo",
      "location": "Beijing, Beijing, China",
      "salary": "Not specified",
      "description": "LinkedIn Job - Software Engineer I",
      "source": "LinkedIn",
      "url": "https://cn.linkedin.com/jobs/view/software-engineer-i-at-duolingo-4408020736?position=4&pageNum=0&refId=l715izhDauHZ2kxgtRyZ8A%3D%3D&trackingId=%2FJGBBpbiBa5%2FG9oHTc45dg%3D%3D",
      "posted_at": "2026-05-02T09:57:07.007064"
    },
    {
      "title": "Software Engineer",
      "company": "Swiggy",
      "location": "India",
      "salary": "Not specified",
      "description": "LinkedIn Job - Software Engineer",
      "source": "LinkedIn",
      "url": "https://in.linkedin.com/jobs/view/software-engineer-at-swiggy-4407833112?position=5&pageNum=0&refId=l715izhDauHZ2kxgtRyZ8A%3D%3D&trackingId=QCsjteANmojZmgBTqh84aQ%3D%3D",
      "posted_at": "2026-05-02T09:57:07.007241"
    },
    {
      "title": "Software Development Engineer I",
      "company": "Kotak Mahindra Bank",
      "location": "Bengaluru, Karnataka, India",
      "salary": "Not specified",
      "description": "LinkedIn Job - Software Development Engineer I",
      "source": "LinkedIn",
      "url": "https://in.linkedin.com/jobs/view/software-development-engineer-i-at-kotak-mahindra-bank-4409050276?position=6&pageNum=0&refId=l715izhDauHZ2kxgtRyZ8A%3D%3D&trackingId=zaQUGRSGYB8Vd0c0Hwkjdg%3D%3D",
      "posted_at": "2026-05-02T09:57:07.007452"
    },
    {
      "title": "Software Engineer 2",
      "company": "Microsoft",
      "location": "Hyderabad, Telangana, India",
      "salary": "Not specified",
      "description": "LinkedIn Job - Software Engineer 2",
      "source": "LinkedIn",
      "url": "https://in.linkedin.com/jobs/view/software-engineer-2-at-microsoft-4387948593?position=7&pageNum=0&refId=l715izhDauHZ2kxgtRyZ8A%3D%3D&trackingId=XyST2BYe65APtHFRKk5kvQ%3D%3D",
      "posted_at": "2026-05-02T09:57:07.007633"
    },
    {
      "title": "Graduate software engineer",
      "company": "Evernote",
      "location": "Cambridge, England, United Kingdom",
      "salary": "Not specified",
      "description": "LinkedIn Job - Graduate software engineer",
      "source": "LinkedIn",
      "url": "https://uk.linkedin.com/jobs/view/graduate-software-engineer-at-evernote-4406581268?position=8&pageNum=0&refId=l715izhDauHZ2kxgtRyZ8A%3D%3D&trackingId=z41R8qvnZmJXTTwet1mB4g%3D%3D",
      "posted_at": "2026-05-02T09:57:07.007814"
    },
    {
      "title": "Software Engineer",
      "company": "Kotak Mahindra Bank",
      "location": "Bengaluru, Karnataka, India",
      "salary": "Not specified",
      "description": "LinkedIn Job - Software Engineer",
      "source": "LinkedIn",
      "url": "https://in.linkedin.com/jobs/view/software-engineer-at-kotak-mahindra-bank-4408203925?position=9&pageNum=0&refId=l715izhDauHZ2kxgtRyZ8A%3D%3D&trackingId=xmG5%2Fwdn7VrrbW6KtdFjWQ%3D%3D",
      "posted_at": "2026-05-02T09:57:07.007986"
    },
    {
      "title": "Python Developer",
      "company": "Infosys",
      "location": "Bengaluru, Karnataka, India",
      "salary": "Not specified",
      "description": "LinkedIn Job - Python Developer",
      "source": "LinkedIn",
      "url": "https://in.linkedin.com/jobs/view/python-developer-at-infosys-4323369504?position=1&pageNum=0&refId=e6vJyLRDkzopBD75uBYUQg%3D%3D&trackingId=dISfov5QoHxhIcRuXgQr0A%3D%3D",
      "posted_at": "2026-05-02T09:57:09.987139"
    },
    {
      "title": "Software Engineer (Python) - AI Platform",
      "company": "Revolut",
      "location": "United Arab Emirates",
      "salary": "Not specified",
      "description": "LinkedIn Job - Software Engineer (Python) - AI Platform",
      "source": "LinkedIn",
      "url": "https://ae.linkedin.com/jobs/view/software-engineer-python-ai-platform-at-revolut-4250198849?position=3&pageNum=0&refId=e6vJyLRDkzopBD75uBYUQg%3D%3D&trackingId=TkR25UFBJ0%2FL20P3fnCmOw%3D%3D",
      "posted_at": "2026-05-02T09:57:09.987679"
    },
    {
      "title": "Associate - Python Data Engineer - GDC",
      "company": "PwC India",
      "location": "Kolkata, West Bengal, India",
      "salary": "Not specified",
      "description": "LinkedIn Job - Associate - Python Data Engineer - GDC",
      "source": "LinkedIn",
      "url": "https://in.linkedin.com/jobs/view/associate-python-data-engineer-gdc-at-pwc-india-4291069034?position=7&pageNum=0&refId=e6vJyLRDkzopBD75uBYUQg%3D%3D&trackingId=C5TKVmAkTaZGJEG2XubCfQ%3D%3D",
      "posted_at": "2026-05-02T09:57:09.988424"
    },
    {
      "title": "Software Engineer (Python)",
      "company": "Cisco",
      "location": "Cracow, Małopolskie, Poland",
      "salary": "Not specified",
      "description": "LinkedIn Job - Software Engineer (Python)",
      "source": "LinkedIn",
      "url": "https://pl.linkedin.com/jobs/view/software-engineer-python-at-cisco-4407831137?position=10&pageNum=0&refId=e6vJyLRDkzopBD75uBYUQg%3D%3D&trackingId=7%2BaumWewzHCBIHKWFIdYRA%3D%3D",
      "posted_at": "2026-05-02T09:57:09.989104"
    },
    {
      "title": "ReactJS Developer",
      "company": "Tata Elxsi",
      "location": "Pune City, Maharashtra, India",
      "salary": "Not specified",
      "description": "LinkedIn Job - ReactJS Developer",
      "source": "LinkedIn",
      "url": "https://in.linkedin.com/jobs/view/reactjs-developer-at-tata-elxsi-4402103782?position=1&pageNum=0&refId=jHdd8gHMJYYnzTrLVyInPw%3D%3D&trackingId=djq9l8A0svahNif8tjBamA%3D%3D",
      "posted_at": "2026-05-02T09:57:12.954852"
    },
    {
      "title": "SDE II / III - Frontend Developer",
      "company": "ZEE - Technology & Innovation",
      "location": "Bengaluru, Karnataka, India",
      "salary": "Not specified",
      "description": "LinkedIn Job - SDE II / III - Frontend Developer",
      "source": "LinkedIn",
      "url": "https://in.linkedin.com/jobs/view/sde-ii-iii-frontend-developer-at-zee-technology-innovation-4308021555?position=2&pageNum=0&refId=jHdd8gHMJYYnzTrLVyInPw%3D%3D&trackingId=oANn8bRDnbAFw6Vy09NO7g%3D%3D",
      "posted_at": "2026-05-02T09:57:12.955064"
    },
    {
      "title": "Frontend Developer",
      "company": "Alike",
      "location": "Gurugram, Haryana, India",
      "salary": "Not specified",
      "description": "LinkedIn Job - Frontend Developer",
      "source": "LinkedIn",
      "url": "https://in.linkedin.com/jobs/view/frontend-developer-at-alike-4383814464?position=3&pageNum=0&refId=jHdd8gHMJYYnzTrLVyInPw%3D%3D&trackingId=3ccJ4vkzYisrXuNotE24jA%3D%3D",
      "posted_at": "2026-05-02T09:57:12.955287"
    },
    {
      "title": "React Developer",
      "company": "Infosys",
      "location": "Bengaluru East, Karnataka, India",
      "salary": "Not specified",
      "description": "LinkedIn Job - React Developer",
      "source": "LinkedIn",
      "url": "https://in.linkedin.com/jobs/view/react-developer-at-infosys-4394429035?position=4&pageNum=0&refId=jHdd8gHMJYYnzTrLVyInPw%3D%3D&trackingId=DHYRXirdsf%2F40%2Fnu9ClDdg%3D%3D",
      "posted_at": "2026-05-02T09:57:12.955547"
    },
    {
      "title": "Junior Full Stack Developer",
      "company": "Meyer Distributing",
      "location": "Indianapolis, IN",
      "salary": "Not specified",
      "description": "LinkedIn Job - Junior Full Stack Developer",
      "source": "LinkedIn",
      "url": "https://www.linkedin.com/jobs/view/junior-full-stack-developer-at-meyer-distributing-4408031590?position=5&pageNum=0&refId=jHdd8gHMJYYnzTrLVyInPw%3D%3D&trackingId=0Lx9rLjICQADwiAKZZ0%2BEQ%3D%3D",
      "posted_at": "2026-05-02T09:57:12.955760"
    },
    {
      "title": "Frontend Developer",
      "company": "INDICO by Telkomsel",
      "location": "Jakarta, Jakarta, Indonesia",
      "salary": "Not specified",
      "description": "LinkedIn Job - Frontend Developer",
      "source": "LinkedIn",
      "url": "https://id.linkedin.com/jobs/view/frontend-developer-at-indico-by-telkomsel-4408212274?position=6&pageNum=0&refId=jHdd8gHMJYYnzTrLVyInPw%3D%3D&trackingId=9rZ6OqFgWjMHra9lqpIOYw%3D%3D",
      "posted_at": "2026-05-02T09:57:12.955989"
    },
    {
      "title": "Frontend Developer",
      "company": "Unacademy",
      "location": "Bengaluru, Karnataka, India",
      "salary": "Not specified",
      "description": "LinkedIn Job - Frontend Developer",
      "source": "LinkedIn",
      "url": "https://in.linkedin.com/jobs/view/frontend-developer-at-unacademy-4395978950?position=7&pageNum=0&refId=jHdd8gHMJYYnzTrLVyInPw%3D%3D&trackingId=j3scWbNKmY3Xls3%2FiiFkAA%3D%3D",
      "posted_at": "2026-05-02T09:57:12.956223"
    },
    {
      "title": "React JS Developer",
      "company": "Infosys",
      "location": "Hyderabad, Telangana, India",
      "salary": "Not specified",
      "description": "LinkedIn Job - React JS Developer",
      "source": "LinkedIn",
      "url": "https://in.linkedin.com/jobs/view/react-js-developer-at-infosys-4393032766?position=8&pageNum=0&refId=jHdd8gHMJYYnzTrLVyInPw%3D%3D&trackingId=0lRwd3qJTuKL%2BOdUDUMsVQ%3D%3D",
      "posted_at": "2026-05-02T09:57:12.956469"
    },
    {
      "title": "Full-Stack Developer Internship",
      "company": "Acowale",
      "location": "Bengaluru, Karnataka, India",
      "salary": "Not specified",
      "description": "LinkedIn Job - Full-Stack Developer Internship",
      "source": "LinkedIn",
      "url": "https://in.linkedin.com/jobs/view/full-stack-developer-internship-at-acowale-4406520776?position=9&pageNum=0&refId=jHdd8gHMJYYnzTrLVyInPw%3D%3D&trackingId=0IGYqKOx2qlWmWySwbuIOg%3D%3D",
      "posted_at": "2026-05-02T09:57:12.956679"
    },
    {
      "title": "Frontend Developer",
      "company": "ShyftLabs",
      "location": "Hyderabad, Telangana, India",
      "salary": "Not specified",
      "description": "LinkedIn Job - Frontend Developer",
      "source": "LinkedIn",
      "url": "https://in.linkedin.com/jobs/view/frontend-developer-at-shyftlabs-4302540393?position=10&pageNum=0&refId=jHdd8gHMJYYnzTrLVyInPw%3D%3D&trackingId=pnhpASnVnOvUiDqwv3T0fg%3D%3D",
      "posted_at": "2026-05-02T09:57:12.956889"
    },
    {
      "title": "Data Scientist - H/F",
      "company": "L’univers NOZ",
      "location": "Saint-Berthevin, Pays de la Loire, France",
      "salary": "Not specified",
      "description": "LinkedIn Job - Data Scientist - H/F",
      "source": "LinkedIn",
      "url": "https://fr.linkedin.com/jobs/view/data-scientist-h-f-at-l%E2%80%99univers-noz-4407877395?position=1&pageNum=0&refId=dXKlbJY1mXbAyifsFq%2Bx4A%3D%3D&trackingId=yBHxfaf4pC%2BGW9wn6hcX%2BA%3D%3D",
      "posted_at": "2026-05-02T09:57:16.015934"
    },
    {
      "title": "Data Scientist",
      "company": "Tinder",
      "location": "Los Angeles, CA",
      "salary": "Not specified",
      "description": "LinkedIn Job - Data Scientist",
      "source": "LinkedIn",
      "url": "https://www.linkedin.com/jobs/view/data-scientist-at-tinder-4407688060?position=2&pageNum=0&refId=dXKlbJY1mXbAyifsFq%2Bx4A%3D%3D&trackingId=JtXNhrAMQwO6Xa8e9DSXSw%3D%3D",
      "posted_at": "2026-05-02T09:57:16.016187"
    },
    {
      "title": "Data Scientist",
      "company": "Flipkart",
      "location": "Bengaluru, Karnataka, India",
      "salary": "Not specified",
      "description": "LinkedIn Job - Data Scientist",
      "source": "LinkedIn",
      "url": "https://in.linkedin.com/jobs/view/data-scientist-at-flipkart-4407352161?position=4&pageNum=0&refId=dXKlbJY1mXbAyifsFq%2Bx4A%3D%3D&trackingId=UhO%2B8Xit2DJMhXDg669BDw%3D%3D",
      "posted_at": "2026-05-02T09:57:16.016620"
    },
    {
      "title": "Machine Learning Engineer",
      "company": "Coforge",
      "location": "Richmond, VA",
      "salary": "Not specified",
      "description": "LinkedIn Job - Machine Learning Engineer",
      "source": "LinkedIn",
      "url": "https://www.linkedin.com/jobs/view/machine-learning-engineer-at-coforge-4406546129?position=6&pageNum=0&refId=dXKlbJY1mXbAyifsFq%2Bx4A%3D%3D&trackingId=9Ksd3%2FCiBChDh9mfXJdB6Q%3D%3D",
      "posted_at": "2026-05-02T09:57:16.017030"
    },
    {
      "title": "Data Scientist I",
      "company": "Banco Bradesco",
      "location": "Osasco, São Paulo, Brazil",
      "salary": "Not specified",
      "description": "LinkedIn Job - Data Scientist I",
      "source": "LinkedIn",
      "url": "https://br.linkedin.com/jobs/view/data-scientist-i-at-banco-bradesco-4409039228?position=7&pageNum=0&refId=dXKlbJY1mXbAyifsFq%2Bx4A%3D%3D&trackingId=1YrrVt4i737eaxgRqHMS9A%3D%3D",
      "posted_at": "2026-05-02T09:57:16.017265"
    },
    {
      "title": "Machine Learning Engineer",
      "company": "Meltwater",
      "location": "New York, NY",
      "salary": "Not specified",
      "description": "LinkedIn Job - Machine Learning Engineer",
      "source": "LinkedIn",
      "url": "https://www.linkedin.com/jobs/view/machine-learning-engineer-at-meltwater-4406297687?position=8&pageNum=0&refId=dXKlbJY1mXbAyifsFq%2Bx4A%3D%3D&trackingId=kp6diyPgZBTTYLGnkZFRpg%3D%3D",
      "posted_at": "2026-05-02T09:57:16.017478"
    },
    {
      "title": "Data Scientist",
      "company": "ARAUCO",
      "location": "Concepcion, Biobío Region, Chile",
      "salary": "Not specified",
      "description": "LinkedIn Job - Data Scientist",
      "source": "LinkedIn",
      "url": "https://cl.linkedin.com/jobs/view/data-scientist-at-arauco-4408023785?position=9&pageNum=0&refId=dXKlbJY1mXbAyifsFq%2Bx4A%3D%3D&trackingId=RD4eYc6QoR%2BDlwlnaM9xtw%3D%3D",
      "posted_at": "2026-05-02T09:57:16.017658"
    },
    {
      "title": "Data Scientist",
      "company": "Roku",
      "location": "New York, NY",
      "salary": "Not specified",
      "description": "LinkedIn Job - Data Scientist",
      "source": "LinkedIn",
      "url": "https://www.linkedin.com/jobs/view/data-scientist-at-roku-4359751153?position=10&pageNum=0&refId=dXKlbJY1mXbAyifsFq%2Bx4A%3D%3D&trackingId=0XAkY4ETg%2FXnbnkKgrL08g%3D%3D",
      "posted_at": "2026-05-02T09:57:16.017834"
    },
    {
      "title": "Devops Engineer",
      "company": "MedReview Inc.",
      "location": "Newport Beach, CA",
      "salary": "Not specified",
      "description": "LinkedIn Job - Devops Engineer",
      "source": "LinkedIn",
      "url": "https://www.linkedin.com/jobs/view/devops-engineer-at-medreview-inc-4399902206?position=1&pageNum=0&refId=CdvMY1JRtsOzncBKQF4ngg%3D%3D&trackingId=GuHNi%2BV7laB9bzfNRyAkgw%3D%3D",
      "posted_at": "2026-05-02T09:57:19.088224"
    },
    {
      "title": "DevOps Engineer",
      "company": "Easebuzz",
      "location": "Pune Division, Maharashtra, India",
      "salary": "Not specified",
      "description": "LinkedIn Job - DevOps Engineer",
      "source": "LinkedIn",
      "url": "https://in.linkedin.com/jobs/view/devops-engineer-at-easebuzz-4218857089?position=2&pageNum=0&refId=CdvMY1JRtsOzncBKQF4ngg%3D%3D&trackingId=N5I3Hv61L8BCG%2B7Om6%2F%2FBQ%3D%3D",
      "posted_at": "2026-05-02T09:57:19.088543"
    },
    {
      "title": "DevOps Engineer",
      "company": "Infopro Digital",
      "location": "Atlanta, GA",
      "salary": "Not specified",
      "description": "LinkedIn Job - DevOps Engineer",
      "source": "LinkedIn",
      "url": "https://www.linkedin.com/jobs/view/devops-engineer-at-infopro-digital-4409414901?position=3&pageNum=0&refId=CdvMY1JRtsOzncBKQF4ngg%3D%3D&trackingId=KmEmpE%2FWx7SoLUHP%2FDtt%2FQ%3D%3D",
      "posted_at": "2026-05-02T09:57:19.088731"
    },
    {
      "title": "DevOps Engineer",
      "company": "Connecteam",
      "location": "Tel Aviv-Yafo, Tel Aviv District, Israel",
      "salary": "Not specified",
      "description": "LinkedIn Job - DevOps Engineer",
      "source": "LinkedIn",
      "url": "https://il.linkedin.com/jobs/view/devops-engineer-at-connecteam-4290904319?position=4&pageNum=0&refId=CdvMY1JRtsOzncBKQF4ngg%3D%3D&trackingId=EzDGm66PLlTU8b6Y9ERAUw%3D%3D",
      "posted_at": "2026-05-02T09:57:19.088911"
    },
    {
      "title": "DevOps Engineer",
      "company": "Infosys",
      "location": "Hyderabad, Telangana, India",
      "salary": "Not specified",
      "description": "LinkedIn Job - DevOps Engineer",
      "source": "LinkedIn",
      "url": "https://in.linkedin.com/jobs/view/devops-engineer-at-infosys-4392106338?position=5&pageNum=0&refId=CdvMY1JRtsOzncBKQF4ngg%3D%3D&trackingId=WNh5YQjc1z6dgoMmZE4H1g%3D%3D",
      "posted_at": "2026-05-02T09:57:19.089080"
    },
    {
      "title": "DevOps Engineer",
      "company": "LightFeather",
      "location": "Washington, DC",
      "salary": "Not specified",
      "description": "LinkedIn Job - DevOps Engineer",
      "source": "LinkedIn",
      "url": "https://www.linkedin.com/jobs/view/devops-engineer-at-lightfeather-4408786713?position=7&pageNum=0&refId=CdvMY1JRtsOzncBKQF4ngg%3D%3D&trackingId=DwODzE9rHz9CvlnuTkm3mQ%3D%3D",
      "posted_at": "2026-05-02T09:57:19.089458"
    },
    {
      "title": "Jr Devops Engineer",
      "company": "OVA.Work",
      "location": "New York, NY",
      "salary": "Not specified",
      "description": "LinkedIn Job - Jr Devops Engineer",
      "source": "LinkedIn",
      "url": "https://www.linkedin.com/jobs/view/jr-devops-engineer-at-ova-work-4398356898?position=9&pageNum=0&refId=CdvMY1JRtsOzncBKQF4ngg%3D%3D&trackingId=LN01jvwsCcXhQen2VMpKJw%3D%3D",
      "posted_at": "2026-05-02T09:57:19.089810"
    },
    {
      "title": "junior devops engineer",
      "company": "OVA.Work",
      "location": "Alpharetta, GA",
      "salary": "Not specified",
      "description": "LinkedIn Job - junior devops engineer",
      "source": "LinkedIn",
      "url": "https://www.linkedin.com/jobs/view/junior-devops-engineer-at-ova-work-4309344701?position=10&pageNum=0&refId=CdvMY1JRtsOzncBKQF4ngg%3D%3D&trackingId=F%2FGqqfZWSx0IsAyJX6qEGw%3D%3D",
      "posted_at": "2026-05-02T09:57:19.089975"
    }
  ]
}